{
	"info": {
		"_postman_id": "9180c15c-bc52-4982-81ed-fe06e53514f8",
		"name": "mern-excercise-tracker",
		"schema": "https://schema.getpostman.com/json/collection/v2.1.0/collection.json",
		"_exporter_id": "43597602",
		"_collection_link": "https://siddhantbali.postman.co/workspace/Siddhant-Bali's-Workspace~aa45828a-f45f-44f3-88be-317b8266fb88/collection/43597602-9180c15c-bc52-4982-81ed-fe06e53514f8?action=share&source=collection_link&creator=43597602"
	},
	"item": [
		{
			"name": "/users/add",
			"request": {
				"method": "POST",
				"header": [],
				"body": {
					"mode": "raw",
					"raw": "{\n    \"username\":\"bhaskar\"\n}",
					"options": {
						"raw": {
							"language": "json"
						}
					}
				},
				"url": {
					"raw": "{{baseURL}}/users/add",
					"host": [
						"{{baseURL}}"
					],
					"path": [
						"users",
						"add"
					]
				}
			},
			"response": []
		},
		{
			"name": "/users/",
			"request": {
				"method": "GET",
				"header": [],
				"url": {
					"raw": "{{baseURL}}/users/",
					"host": [
						"{{baseURL}}"
					],
					"path": [
						"users",
						""
					]
				}
			},
			"response": []
		},
		{
			"name": "/exercises/add",
			"request": {
				"method": "POST",
				"header": [],
				"body": {
					"mode": "raw",
					"raw": "{\n    \"username\":\"bhati\",\n    \"description\":\"Deadlift\",\n    \"duration\": \"11\" ,\n    \"date\":\"2025-08-30T19:03:24.994Z\"\n}",
					"options": {
						"raw": {
							"language": "json"
						}
					}
				},
				"url": {
					"raw": "{{baseURL}}/exercises/add",
					"host": [
						"{{baseURL}}"
					],
					"path": [
						"exercises",
						"add"
					]
				}
			},
			"response": []
		},
		{
			"name": "/exercises/",
			"protocolProfileBehavior": {
				"disableBodyPruning": true
			},
			"request": {
				"method": "GET",
				"header": [],
				"body": {
					"mode": "raw",
					"raw": "{\n    \"username\":\"bhati\",\n    \"description\":\"Deadlift\",\n    \"duration\": \"11\" ,\n    \"date\":\"2025-08-30T19:03:24.994Z\"\n}",
					"options": {
						"raw": {
							"language": "json"
						}
					}
				},
				"url": {
					"raw": "{{baseURL}}/exercises/",
					"host": [
						"{{baseURL}}"
					],
					"path": [
						"exercises",
						""
					]
				}
			},
			"response": []
		},
		{
			"name": "/exercises/:id",
			"protocolProfileBehavior": {
				"disableBodyPruning": true
			},
			"request": {
				"method": "GET",
				"header": [],
				"body": {
					"mode": "raw",
					"raw": "",
					"options": {
						"raw": {
							"language": "json"
						}
					}
				},
				"url": {
					"raw": "{{baseURL}}/exercises/688a6fee71069ae17aa9e424",
					"host": [
						"{{baseURL}}"
					],
					"path": [
						"exercises",
						"688a6fee71069ae17aa9e424"
					]
				}
			},
			"response": []
		},
		{
			"name": "/exercises/update/:id",
			"request": {
				"method": "POST",
				"header": [],
				"body": {
					"mode": "raw",
					"raw": "        {\n        \"username\": \"bhaskar\",\n        \"description\": \"Mountain Climbing\",\n        \"duration\": 9,\n        \"date\": \"2025-08-30T19:03:24.994Z\"\n        }",
					"options": {
						"raw": {
							"language": "json"
						}
					}
				},
				"url": {
					"raw": "{{baseURL}}/exercises/update/688a6fee71069ae17aa9e424",
					"host": [
						"{{baseURL}}"
					],
					"path": [
						"exercises",
						"update",
						"688a6fee71069ae17aa9e424"
					]
				}
			},
			"response": []
		},
		{
			"name": "/users/update/:username",
			"request": {
				"method": "POST",
				"header": [],
				"body": {
					"mode": "raw",
					"raw": "        {\n        \"username\": \"Siddhant Bali\"\n        }",
					"options": {
						"raw": {
							"language": "json"
						}
					}
				},
				"url": {
					"raw": "{{baseURL}}/username/update/bali",
					"host": [
						"{{baseURL}}"
					],
					"path": [
						"username",
						"update",
						"bali"
					]
				}
			},
			"response": []
		},
		{
			"name": "/exercises/delete/:id",
			"request": {
				"method": "DELETE",
				"header": [],
				"body": {
					"mode": "raw",
					"raw": " {\n            \"username\": \"bhati\",\n            \"description\": \"Deadlift\",\n            \"duration\": 11,\n            \"date\": \"2025-08-30T19:03:24.994Z\",\n        }",
					"options": {
						"raw": {
							"language": "json"
						}
					}
				},
				"url": {
					"raw": "{{baseURL}}/exercises/delete/688a707071069ae17aa9e428",
					"host": [
						"{{baseURL}}"
					],
					"path": [
						"exercises",
						"delete",
						"688a707071069ae17aa9e428"
					]
				}
			},
			"response": []
		},
		{
			"name": "/users/delete/:username",
			"request": {
				"method": "DELETE",
				"header": [],
				"body": {
					"mode": "raw",
					"raw": " {\n            \"username\": \"bhati\"\n        }",
					"options": {
						"raw": {
							"language": "json"
						}
					}
				},
				"url": {
					"raw": "{{baseURL}}/users/delete/bhati",
					"host": [
						"{{baseURL}}"
					],
					"path": [
						"users",
						"delete",
						"bhati"
					]
				}
			},
			"response": []
		}
	],
	"variable": [
		{
			"key": "baseURL",
			"value": "http://localhost:5000",
			"type": "default"
		}
	]
}